SchemaRegistryLibrary/Client.py
SchemaRegistryLibrary/Seliarizer.py
SchemaRegistryLibrary/Utils.py
SchemaRegistryLibrary/__init__.py
SchemaRegistryLibrary/version.py
robotframework_schemaregistrylibrary-0.0.2.dist-info/LICENSE
robotframework_schemaregistrylibrary-0.0.2.dist-info/METADATA
robotframework_schemaregistrylibrary-0.0.2.dist-info/WHEEL
robotframework_schemaregistrylibrary-0.0.2.dist-info/top_level.txt
robotframework_schemaregistrylibrary-0.0.2.dist-info/RECORD
